pytest_vulture/__init__.py
pytest_vulture/plugin.py
pytest_vulture/py.typed
pytest_vulture/setup_manager.py
pytest_vulture/conf/__init__.py
pytest_vulture/conf/base.py
pytest_vulture/conf/package.py
pytest_vulture/conf/reader.py
pytest_vulture/conf/vulture.py
pytest_vulture/vulture/__init__.py
pytest_vulture/vulture/comment.py
pytest_vulture/vulture/manager.py
pytest_vulture-2.2.2.dist-info/METADATA
pytest_vulture-2.2.2.dist-info/WHEEL
pytest_vulture-2.2.2.dist-info/entry_points.txt
pytest_vulture-2.2.2.dist-info/licenses/LICENSE
pytest_vulture-2.2.2.dist-info/RECORD
