Metadata-Version: 2.3
Name: pytest-vulture
Version: 2.2.2
Summary: A pytest plugin to checks dead code with vulture
Project-URL: Homepage, https://github.com/Gatewatcher/pytest-vulture/
Project-URL: Bug Reports, https://github.com/Gatewatcher/pytest-vulture/issues
Project-URL: Source, https://github.com/Gatewatcher/pytest-vulture/
Author-email: Abadie Moran <moran.abadie@gatewatcher.com>
Maintainer-email: Abadie Moran <moran.abadie@gatewatcher.com>
License: MIT
Keywords: code analysis,dead code,pytest,testing,vulture
Classifier: Framework :: Pytest
Classifier: Intended Audience :: Developers
Classifier: License :: OSI Approved :: MIT License
Classifier: Programming Language :: Python :: 3
Classifier: Programming Language :: Python :: 3 :: Only
Classifier: Programming Language :: Python :: 3.7
Classifier: Programming Language :: Python :: 3.8
Classifier: Programming Language :: Python :: 3.9
Classifier: Programming Language :: Python :: 3.10
Classifier: Programming Language :: Python :: 3.11
Classifier: Programming Language :: Python :: 3.12
Classifier: Programming Language :: Python :: Implementation :: PyPy
Classifier: Topic :: Software Development :: Quality Assurance
Classifier: Topic :: Software Development :: Testing
Requires-Python: >=3.7
Requires-Dist: pytest>=7.0.0
Requires-Dist: vulture<3.0,>=2.0
